main.py
hyuk_lang-1.0.0a1.dist-info/licenses/LICENSE
hyuk_lang-1.0.0a1.dist-info/METADATA
hyuk_lang-1.0.0a1.dist-info/WHEEL
hyuk_lang-1.0.0a1.dist-info/top_level.txt
hyuk_lang-1.0.0a1.dist-info/RECORD
