Metadata-Version: 2.4
Name: hyuk-lang
Version: 1.0.0a1
Summary: A Brainfuck-like esoteric language called Hyuk
Author-email: JoonwooM <mjoonwoo@gmail.com>
License: MIT License
Requires-Python: >=3.8
License-File: LICENSE
Dynamic: license-file
